{
  "Changes": [
    {
      "Action": "EditData",
      "Target": "Characters/Dialogue/Claire",
      "Entries": {
        //SPECIAL DIALOGUE
        "Introduction": "{{i18n:Claire.CharacterDialogue.001}}",
        "pamHouseUpgrade": "{{i18n:Claire.CharacterDialogue.002}}",
        "pamHouseUpgradeAnonymous": "{{i18n:Claire.CharacterDialogue.002}}",
        "accept_614": "{{i18n:Claire.CharacterDialogue.003}}",
        "Town_92_44": "{{i18n:Claire.CharacterDialogue.004}}",
        "danceRejection": "{{i18n:Claire.CharacterDialogue.005}}",
        "BusStop_12_8": "{{i18n:Claire.CharacterDialogue.006}}",
        "movieTheaterClaire": "{{i18n:Claire.CharacterDialogue.007}}",
        "breakUp": "{{i18n:Claire.CharacterDialogue.008}}",
        "dumped_Girls": "{{i18n:Claire.CharacterDialogue.009}}",
        "secondChance_Girls": "{{i18n:Claire.CharacterDialogue.010}}",
        "divorced": "{{i18n:Claire.CharacterDialogue.011}}",
        "Resort_Entering": "{{i18n:Claire.CharacterDialogue.012}}",
        "Resort_Leaving": "{{i18n:Claire.CharacterDialogue.013}}",
        "Resort_Shore": "{{i18n:Claire.CharacterDialogue.014}}",
        "Resort_Chair": "{{i18n:Claire.CharacterDialogue.015}}",
        "Resort_Bar": "{{i18n:Claire.CharacterDialogue.016}}",
        "Resort": "{{i18n:Claire.CharacterDialogue.017}}",
        "GreenRain": "{{i18n:Claire.GreenRain}}",
        "GreenRainFinished": "{{i18n:Claire.GreenRainFinished}}",
        "GreenRain_2": "{{i18n:Claire.GreenRain2}}",
        "AcceptGift_(O)StardropTea": "{{i18n:Claire.GiftStardropTea}}",
        "AcceptGift_(O)614": "{{i18n:Claire.Gift614}}",
        "AcceptGift_(O)349": "{{i18n:Claire.Gift349}}",
        "AcceptGift_(O)618": "{{i18n:Claire.Gift618}}",
        "AcceptGift_(O)560": "{{i18n:Claire.Gift560}}",
        "AcceptGift_(O)167": "{{i18n:Claire.Gift167}}",
        "AcceptGift_(O)342": "{{i18n:Claire.Gift342}}",
        "AcceptGift_book_item": "{{i18n:Claire.GiftBook}}",
        "AcceptBirthdayGift_Positive": "{{i18n:Claire.GiftBDpos}}",
        "AcceptBirthdayGift_Negative": "{{i18n:Claire.GiftBDneg}}",
        "dating_Claire_memory_twoweeks": "{{i18n:Claire.datingTwoWeek}}",
        //SPRING AND GENERAL DIALOGUE
        "Mon": "{{i18n:Claire.CharacterDialogue.018}}",
        "Mon2": "{{i18n:Claire.CharacterDialogue.019}}",
        "Mon6": "{{i18n:Claire.CharacterDialogue.020}}",
        "Tue": "{{i18n:Claire.CharacterDialogue.021}}",
        "Tue4": "{{i18n:Claire.CharacterDialogue.022}}",
        "Tue8": "{{i18n:Claire.CharacterDialogue.023}}",
        "Wed": "{{i18n:Claire.CharacterDialogue.024}}",
        "Wed2": "{{i18n:Claire.CharacterDialogue.025}}",
        "Wed6": "{{i18n:Claire.CharacterDialogue.026}}",
        "Thu": "{{i18n:Claire.CharacterDialogue.027}}",
        "Thu4": "{{i18n:Claire.CharacterDialogue.028}}",
        "Thu8": "{{i18n:Claire.CharacterDialogue.029}}",
        "Fri": "{{i18n:Claire.CharacterDialogue.030}}",
        "Fri4": "{{i18n:Claire.CharacterDialogue.031}}",
        "Sat": "{{i18n:Claire.CharacterDialogue.032}}",
        "Sat2": "{{i18n:Claire.CharacterDialogue.033}}",
        "Sat4": "{{i18n:Claire.CharacterDialogue.034}}",
        "Sat8": "{{i18n:Claire.CharacterDialogue.035}}",
        "Sun": "{{i18n:Claire.CharacterDialogue.036}}",
        "Sun2": "{{i18n:Claire.CharacterDialogue.037}}",
        "Sun4": "{{i18n:Claire.CharacterDialogue.038}}",
        "Sun8": "{{i18n:Claire.CharacterDialogue.039}}",
        //SUMMER DIALOGUE
        "summer_1": "{{i18n:Claire.CharacterDialogue.040}}",
        "summer_10": "{{i18n:Claire.CharacterDialogue.041}}",
        "summer_18": "{{i18n:Claire.CharacterDialogue.042}}",
        //"summer_28": "I'd love to the jellies, but I'll be too tired from working all day...$0",
        "summer_Mon": "{{i18n:Claire.CharacterDialogue.043}}",
        "summer_Mon2": "{{i18n:Claire.CharacterDialogue.044}}",
        "summer_Mon8": "{{i18n:Claire.CharacterDialogue.045}}",
        "summer_Tue6": "{{i18n:Claire.CharacterDialogue.046}}",
        "summer_Wed": "{{i18n:Claire.CharacterDialogue.047}}",
        "summer_Wed4": "{{i18n:Claire.CharacterDialogue.048}}",
        "summer_Wed8": "{{i18n:Claire.CharacterDialogue.049}}",
        "summer_Thu8": "{{i18n:Claire.CharacterDialogue.050}}",
        "summer_Fri2": "{{i18n:Claire.CharacterDialogue.051}}",
        "summer_Fri8": "{{i18n:Claire.CharacterDialogue.052}}",
        "summer_Sun": "{{i18n:Claire.CharacterDialogue.053}}",
        "summer_Sun4": "{{i18n:Claire.CharacterDialogue.054}}",
        "summer_Sun8": "{{i18n:Claire.CharacterDialogue.055}}",
        //FALL DIALOGUE
        "fall_1": "{{i18n:Claire.CharacterDialogue.056}}",
        "fall_6": "{{i18n:Claire.CharacterDialogue.057}}",
        //"fall_15": "{{i18n:Claire.CharacterDialogue.001}}", "So, the Stardew Valley Fair is tomorrow. I'm looking forward to petting the animals.$1#$e#I believe they're Marnie's, correct?$5",
        "fall_19": "{{i18n:Claire.CharacterDialogue.058}}",
        "fall_26": "{{i18n:Claire.CharacterDialogue.059}}",
        "fall_Mon": "{{i18n:Claire.CharacterDialogue.060}}",
        "fall_Mon6": "{{i18n:Claire.CharacterDialogue.061}}",
        "fall_Tue": "{{i18n:Claire.CharacterDialogue.062}}",
        "fall_Tue8": "{{i18n:Claire.CharacterDialogue.063}}",
        "fall_Tue10": "{{i18n:Claire.CharacterDialogue.064}}",
        "fall_Thu8": "{{i18n:Claire.CharacterDialogue.065}}",
        "fall_Wed": "{{i18n:Claire.CharacterDialogue.066}}",
        "fall_Wed2": "{{i18n:Claire.CharacterDialogue.067}}",
        "fall_Wed6": "{{i18n:Claire.CharacterDialogue.068}}",
        "fall_Fri": "{{i18n:Claire.CharacterDialogue.069}}",
        "fall_Fri2": "{{i18n:Claire.CharacterDialogue.070}}",
        "fall_Fri8": "{{i18n:Claire.CharacterDialogue.071}}",
        "fall_Sat8": "{{i18n:Claire.CharacterDialogue.072}}",
        "fall_Sun": "{{i18n:Claire.CharacterDialogue.073}}",
        "fall_Sun2": "{{i18n:Claire.CharacterDialogue.074}}",
        "fall_Sun8": "{{i18n:Claire.CharacterDialogue.075}}",
        //WINTER DIALOGUE
        "winter_1": "{{i18n:Claire.CharacterDialogue.076}}",
        "winter_4": "{{i18n:Claire.CharacterDialogue.077}}",
        "winter_7": "{{i18n:Claire.CharacterDialogue.078}}",
        "winter_21": "{{i18n:Claire.CharacterDialogue.079}}",
        "winter_28": "{{i18n:Claire.CharacterDialogue.080}}",
        "winter_Mon6": "{{i18n:Claire.CharacterDialogue.081}}",
        "winter_Tue": "{{i18n:Claire.CharacterDialogue.082}}",
        "winter_Tue4": "{{i18n:Claire.CharacterDialogue.083}}",
        "winter_Tue8": "{{i18n:Claire.CharacterDialogue.084}}",
        "winter_Wed": "{{i18n:Claire.CharacterDialogue.085}}",
        "winter_Wed4": "{{i18n:Claire.CharacterDialogue.086}}",
        "winter_Thu2": "{{i18n:Claire.CharacterDialogue.087}}",
        "winter_Thu6": "{{i18n:Claire.CharacterDialogue.088}}",
        "winter_Thu10": "{{i18n:Claire.CharacterDialogue.089}}",
        "winter_Sun": "{{i18n:Claire.CharacterDialogue.090}}",
        "winter_Sun2": "{{i18n:Claire.CharacterDialogue.091}}",
        "winter_Sun8": "{{i18n:Claire.CharacterDialogue.092}}",
        //HEART EVENT DIALOGUE
        "claire_event1": "{{i18n:Claire.CharacterDialogue.093}}",
        "claire_event2": "{{i18n:Claire.CharacterDialogue.094}}",
        "claire_event3": "{{i18n:Claire.CharacterDialogue.095}}",
        "claire_event4": "{{i18n:Claire.CharacterDialogue.096}}",
        "claire_event5": "{{i18n:Claire.CharacterDialogue.097}}",
        "claire_event6": "{{i18n:Claire.CharacterDialogue.098}}",
        "claire_event7": "{{i18n:Claire.CharacterDialogue.099}}",
        "claire_event8": "{{i18n:Claire.CharacterDialogue.100}}",
        "claire_event9": "{{i18n:Claire.CharacterDialogue.101}}",
        "claire_event10": "{{i18n:Claire.CharacterDialogue.102}}",
        "claire_event11": "{{i18n:Claire.CharacterDialogue.103}}",
        "claire_event12": "{{i18n:Claire.CharacterDialogue.104}}",
        "claire_event13": "{{i18n:Claire.CharacterDialogue.105}}",
        "claire_event14": "{{i18n:Claire.CharacterDialogue.106}}",
        "claire_event15": "{{i18n:Claire.CharacterDialogue.107}}",
        "claire_event16": "{{i18n:Claire.CharacterDialogue.108}}",
        "claire_event17": "{{i18n:Claire.CharacterDialogue.109}}",
        "claire_event18": "{{i18n:Claire.CharacterDialogue.110}}",
        "claire_event19": "{{i18n:Claire.CharacterDialogue.111}}",
        "claire_event20": "{{i18n:Claire.CharacterDialogue.112}}",
        "claire_event21": "{{i18n:Claire.CharacterDialogue.113}}",
        "claire_event22": "{{i18n:Claire.CharacterDialogue.114}}",
        "claire_event23": "{{i18n:Claire.CharacterDialogue.115}}",
        "claire_event24": "{{i18n:Claire.CharacterDialogue.116}}",
        "claire_event25": "{{i18n:Claire.CharacterDialogue.117}}",
        "claire_event26": "{{i18n:Claire.CharacterDialogue.118}}",
        "claire_event27": "{{i18n:Claire.CharacterDialogue.119}}",
        "claire_event28": "{{i18n:Claire.CharacterDialogue.120}}",
        "claire_event29": "{{i18n:Claire.CharacterDialogue.121}}",
        "claire_event30": "{{i18n:Claire.CharacterDialogue.122}}",
        "claire_event31": "{{i18n:Claire.CharacterDialogue.123}}",
        "claire_event32": "{{i18n:Claire.CharacterDialogue.124}}",
        "claire_event33": "{{i18n:Claire.CharacterDialogue.125}}",
        "claire_event34": "{{i18n:Claire.CharacterDialogue.126}}",
      },
    },
  ]
}