{
	"Name": "Big Conch",
	"Price": 150,
	"Description": "If you put your ear to it, you can hear the ocean.",
	"Category": "Fish",
	"CategoryTextOverride": "",
	"GiftTastes":
	{
	    "Love": [ "Sandy" ],
		"Like": [ "Jas", "GuntherSilvian", "Willy", "Vincent", "Elliott", "Haley" ],
		"Neutral": [ "MarlonFay", "Olivia", "Krobus", "Wizard", "Morgan", "Scarlett", "Lance", "Morgan", "Abigail", "Apples", "Leo", "Sophia", "Claire", "Olivia", "Martin", "Andy", "Victor", "Susan", "MorrisTod", "Alex", "Harvey", "Sam", "Sebastian", "Shane", "Emily", "Leah", "Maru", "Penny", "Caroline", "Clint", "Demetrius", "Dwarf", "Evelyn", "George", "Gus", "Jodi", "Kent", "Lewis", "Linus", "Marnie", "Pam", "Pierre", "Robin" ], 
	},
	"TranslationKey": "object.big-conch",
}